sage/__init__.py
sage/__version__.py
sage/models.py
sage/pipeline.py
sage/py.typed
sage/utils.py
sage/custom_scan/README.md
sage/custom_scan/custom_scan.py
sage/custom_scan/custom_scan_all.py
sage/custom_scan/custom_scan_str.py
sage/custom_scan/concurrency/.dockerignore
sage/custom_scan/concurrency/.gitignore
sage/custom_scan/concurrency/Dockerfile
sage/custom_scan/concurrency/README.md
sage/custom_scan/concurrency/__init__.py
sage/custom_scan/concurrency/docker-compose.yaml
sage/custom_scan/concurrency/poetry.lock
sage/custom_scan/concurrency/pyproject.toml
sage/custom_scan/concurrency/register.py
sage/custom_scan/concurrency/tasks.py
sage/custom_scan/concurrency/trigger.py
sage/custom_scan/concurrency/sage_concurrency_work_dir/.gitkeep
sage/custom_scan/concurrency/sage_concurrency_work_dir/flower_data/.gitkeep
sage/custom_scan/concurrency/sage_concurrency_work_dir/redis_data/.gitkeep
sage/custom_scan/rules/PP006_preprocess_rule_ansible_structure_context.py
sage/process/README.md
sage/process/__init__.py
sage/process/annotations.py
sage/process/ansible_variables.txt
sage/process/knowledge_base.py
sage/process/utils.py
sage/process/variable_resolver.py
sage/tools/file_utils.py
sage/tools/object_report.py
sage/tools/report.py
sage/tools/report_models.py
sage/tools/show_all_fqcn_from_result.py
sage/tools/src_rebuilder.py
sage/tools/summary-sample.json
sage/tools/view_findings.py
sage_scan/__init__.py
sage_scan/__version__.py
sage_scan/ansible_variables.txt
sage_scan/models.py
sage_scan/pipeline.py
sage_scan/py.typed
sage_scan/utils.py
sage_scan/variable_container.py
sage_scan/custom_scan/README.md
sage_scan/custom_scan/custom_scan.py
sage_scan/custom_scan/custom_scan_all.py
sage_scan/custom_scan/custom_scan_process_all.py
sage_scan/custom_scan/custom_scan_str.py
sage_scan/custom_scan/concurrency/.dockerignore
sage_scan/custom_scan/concurrency/.gitignore
sage_scan/custom_scan/concurrency/Dockerfile
sage_scan/custom_scan/concurrency/README.md
sage_scan-0.0.4.dist-info/LICENSE
sage_scan-0.0.4.dist-info/METADATA
sage_scan-0.0.4.dist-info/WHEEL
sage_scan-0.0.4.dist-info/top_level.txt
sage_scan-0.0.4.dist-info/RECORD
