Metadata-Version: 2.1
Name: sage-scan
Version: 0.0.4
Summary: My package description
License: Apache License 2.0
Keywords: one,two
Classifier: Programming Language :: Python :: 3
Requires-Python: >=3.7
License-File: LICENSE
